setup.cfg
setup.py
chemkin/__init__.py
chemkin/chemkin_errors.py
chemkin.egg-info/PKG-INFO
chemkin.egg-info/SOURCES.txt
chemkin.egg-info/dependency_links.txt
chemkin.egg-info/top_level.txt
chemkin/preprocessing/__init__.py
chemkin/preprocessing/parse_xml.py
chemkin/preprocessing/tests/__init__.py
chemkin/preprocessing/tests/test_parse_xml.py
chemkin/reaction/__init__.py
chemkin/reaction/base_rxn.py
chemkin/reaction/elementary_rxn.py
chemkin/reaction/non_elementary_rxn.py
chemkin/reaction/reaction_coefficients.py
chemkin/reaction/tests/__init__.py
chemkin/reaction/tests/test_base_rxn.py
chemkin/reaction/tests/test_elementary_rxn.py
chemkin/reaction/tests/test_non_elementary_rxn.py
chemkin/reaction/tests/test_reaction_coefficients.py
chemkin/solver/ODEint_solver.py
chemkin/solver/__init__.py
chemkin/solver/tests/__init__.py
chemkin/solver/tests/test_ODEint_solver.py
chemkin/thermodynamics/NASA_coef.sqlite
chemkin/thermodynamics/__init__.py
chemkin/thermodynamics/thermo.py
chemkin/thermodynamics/tests/test_thermo.py
chemkin/viz/__init__.py
chemkin/viz/summary.py
chemkin/viz/tests/__init__.py
chemkin/viz/tests/test_summary.py
chemkin/xml-files/rxns.xml
chemkin/xml-files/rxns_hw5.xml
chemkin/xml-files/rxns_ideal.xml
chemkin/xml-files/rxns_irreversible.xml
chemkin/xml-files/rxns_mixed.xml
chemkin/xml-files/rxns_neg_A.xml
chemkin/xml-files/rxns_neg_A_2.xml
chemkin/xml-files/rxns_neg_k.xml
chemkin/xml-files/rxns_non_elementary.xml
chemkin/xml-files/rxns_rev.xml
chemkin/xml-files/rxns_rev_inconsistent.xml
chemkin/xml-files/rxns_rev_neg_A.xml
chemkin/xml-files/rxns_rev_neg_k.xml
chemkin/xml-files/rxns_rev_non_elementary.xml
chemkin/xml-files/rxns_reversible.xml
chemkin/xml-files/rxns_reversible_2.xml
chemkin/xml-files/rxns_reversible_and_irreversible.xml