Metadata-Version: 1.0
Name: chemkin
Version: 3.4
Summary: The best chemkin package
Home-page: https://github.com/G12-cs207-FinalProject/cs207-FinalProject.git
Author: Monsieur Package du Parser
Author-email: nathaniel_stein@g.harvard.edu
License: Harvard
Platform: UNKNOWN
